gpterminator/GPTerminator.py
gpterminator/__init__.py
gpterminator/__main__.py
gpterminator-0.1.11.dist-info/LICENSE
gpterminator-0.1.11.dist-info/METADATA
gpterminator-0.1.11.dist-info/WHEEL
gpterminator-0.1.11.dist-info/entry_points.txt
gpterminator-0.1.11.dist-info/top_level.txt
gpterminator-0.1.11.dist-info/RECORD
