Metadata-Version: 2.1
Name: gpterminator
Version: 0.1.11
Summary: See https://github.com/AineeJames/ChatGPTerminator for more details!
Home-page: https://github.com/AineeJames/ChatGPTerminator
Author: Aiden Olsen
License: LICENSE
Project-URL: Documentation, https://github.com/AineeJames/ChatGPTerminator
Keywords: chatgpt cli python
License-File: LICENSE
Requires-Dist: inquirer (==3.1.3)
Requires-Dist: openai (==0.27.2)
Requires-Dist: prompt-toolkit (==3.0.38)
Requires-Dist: pyperclip (==1.8.2)
Requires-Dist: rich (==13.3.2)
Requires-Dist: tiktoken (==0.3.1)
Requires-Dist: climage (==0.1.3)
